idem_helm/conf.py
idem_helm/version.py
idem_helm/acct/helm/init.py
idem_helm/exec/helm/init.py
idem_helm/exec/helm/release.py
idem_helm/states/__init__.py
idem_helm/states/helm/init.py
idem_helm/states/helm/release.py
idem_helm/tool/__init__.py
idem_helm/tool/helm/command_utils.py
idem_helm/tool/helm/comment_utils.py
idem_helm/tool/helm/release_utils.py
idem_helm/tool/helm/test_state_utils.py
idem_helm-2.0.0.dist-info/LICENSE
idem_helm-2.0.0.dist-info/METADATA
idem_helm-2.0.0.dist-info/WHEEL
idem_helm-2.0.0.dist-info/entry_points.txt
idem_helm-2.0.0.dist-info/top_level.txt
idem_helm-2.0.0.dist-info/RECORD
